{"content":[{"id":"54f87dc4","settings":{"layout":"full_width","gap":"no","height":"min-height","custom_height":{"unit":"vh","size":"100","sizes":[]},"column_position":"stretch","content_position":"middle","structure":"20","custom_height_tablet":{"unit":"px","size":"790","sizes":[]},"_title":"Hero Section","custom_height_mobile":{"unit":"px","size":"890","sizes":[]},"background_background":"classic","padding_mobile":{"unit":"%","top":"","right":"","bottom":"","left":"","isLinked":"1"},"reverse_order_mobile":"reverse-mobile","__globals__":{"background_color":"globals\/colors?id=1fd96a61"},"overflow":"hidden"},"elements":[{"id":"4e86b877","settings":{"_column_size":"50","background_background":"classic","__globals__":{"background_color":"globals\/colors?id=65e875c0"},"_inline_size":"44.962","padding_mobile":{"unit":"%","top":"15","right":"0","bottom":"15","left":"0","isLinked":""}},"elements":[{"id":"30ae2a1","settings":{"image":{"url":"https:\/\/library.elementor.com\/wedding-photographer\/wp-content\/uploads\/sites\/154\/2021\/05\/Roberta_about_pic.jpg","id":"233"},"width":{"unit":"vw","size":"24.7","sizes":[]},"height":{"unit":"vh","size":"59.5","sizes":[]},"object-fit":"cover","width_mobile":{"unit":"vw","size":"72","sizes":[]},"height_mobile":{"unit":"vh","size":"","sizes":[]},"width_tablet":{"unit":"vw","size":"36","sizes":[]},"_animation":"fadeIn"},"elements":[],"isInner":false,"widgetType":"image","elType":"widget"}],"isInner":"","elType":"column"},{"id":"13eadc","settings":{"_column_size":"50","padding":{"unit":"%","top":"0","right":"16","bottom":"0","left":"16","isLinked":""},"padding_mobile":{"unit":"%","top":"20","right":"13","bottom":"8","left":"13","isLinked":""},"_inline_size":"55.012","padding_tablet":{"unit":"%","top":"12","right":"12","bottom":"12","left":"12","isLinked":"1"}},"elements":[{"id":"15cbd602","settings":{"title":"meet Roberta","_margin":{"unit":"%","top":"0","right":"0","bottom":"6","left":"0","isLinked":""},"_margin_tablet":{"unit":"%","top":"0","right":"0","bottom":"10","left":"0","isLinked":""},"align_mobile":"left","header_size":"h1","_padding":{"unit":"%","top":"","right":"","bottom":"","left":"","isLinked":"1"},"__globals__":{"typography_typography":"globals\/typography?id=173baee"},"_margin_mobile":{"unit":"%","top":"","right":"","bottom":"","left":"","isLinked":"1"},"_animation":"fadeIn"},"elements":[],"isInner":false,"widgetType":"heading","elType":"widget"},{"id":"3fa1dfdc","settings":{"editor":"<p>Lorem ipsum dolor sit amet, consectetur adipiscing elit, sed do eiusmod tempor incididunt ut labore et dolore magna aliqua. Non consectetur a erat nam at lectus urna duis convallis. Volutpat lacus laoreet non curabitur gravida arcu ac tortor. Sit amet purus gravida quis.<\/p>\n<p>Ut consequat semper viverra nam libero justo laoreet sit amet. Sit amet mattis vulputate enim nulla aliquet porttitor lacus. Rhoncus urna neque viverra justo nec. Magna ac placerat vestibulum lectus mauris. Sollicitudin ac orci phasellus egestas tellus rutrum. Diam volutpat commodo sed egestas egestas fringilla phasellus faucibus. Nisl rhoncus mattis rhoncus urna neque viverra justo. Enim eu turpis egestas pretium aenean.&nbsp;<\/p>"},"elements":[],"isInner":false,"widgetType":"text-editor","elType":"widget"}],"isInner":"","elType":"column"}],"isInner":"","elType":"section"},{"id":"5dd70e8b","settings":{"content_width":{"unit":"px","size":"890","sizes":[]},"gap":"no","height":"min-height","custom_height":{"unit":"px","size":"870","sizes":[]},"custom_height_tablet":{"unit":"px","size":"750","sizes":[]},"custom_height_mobile":{"unit":"px","size":"590","sizes":[]},"content_position":"middle","background_background":"classic","padding":{"unit":"%","top":"0","right":"4","bottom":"0","left":"4","isLinked":""},"padding_tablet":{"unit":"%","top":"0","right":"6","bottom":"0","left":"6","isLinked":""},"padding_mobile":{"unit":"%","top":"8","right":"8","bottom":"0","left":"8","isLinked":""},"__globals__":{"background_color":"globals\/colors?id=1fd96a61"},"_title":"Testimonial"},"elements":[{"id":"1a7254f","settings":{"_column_size":"100","padding":{"unit":"px","top":"0","right":"0","bottom":"0","left":"50","isLinked":""},"padding_tablet":{"unit":"px","top":"0","right":"0","bottom":"0","left":"45","isLinked":""},"padding_mobile":{"unit":"px","top":"0","right":"0","bottom":"0","left":"40","isLinked":""}},"elements":[{"id":"40438b34","settings":{"content_width":{"unit":"px","size":"840","sizes":[]},"gap":"no","height_inner":"min-height","custom_height_inner":{"unit":"px","size":"403","sizes":[]},"content_position":"middle","background_background":"classic","margin":{"unit":"px","top":"0","right":"0","bottom":"0","left":"0","isLinked":""},"z_index":"5","__globals__":{"background_color":"globals\/colors?id=5daae3fe"}},"elements":[{"id":"487a9b4a","settings":{"_column_size":"100","padding":{"unit":"%","top":"0","right":"14","bottom":"0","left":"14","isLinked":""}},"elements":[{"id":"498f8720","settings":{"selected_icon":{"value":{"url":"https:\/\/library.elementor.com\/wedding-photographer\/wp-content\/uploads\/sites\/154\/2021\/05\/Quotation_mark.svg","id":"245"},"library":"svg"},"align":"left","size":{"unit":"px","size":"42","sizes":[]},"_margin":{"unit":"px","top":"0","right":"0","bottom":"33","left":"0","isLinked":""},"__globals__":{"primary_color":"globals\/colors?id=a856848"},"_animation":"fadeIn"},"elements":[],"isInner":false,"widgetType":"icon","elType":"widget"},{"id":"7e3bd53c","settings":{"testimonial_content":"Weddings are a record event in any love story. Documenting authentic moments of couples and their family's reunion fascinates and excites me over and over again.","testimonial_name":"Roberta Jones","testimonial_job":"","testimonial_alignment":"left","image_size":{"unit":"px","size":"45","sizes":[]},"testimonial_image":{"url":"","id":""},"__globals__":{"name_typography_typography":"globals\/typography?id=3a94527","name_text_color":"globals\/colors?id=secondary"}},"elements":[],"isInner":false,"widgetType":"testimonial","elType":"widget"}],"isInner":"1","elType":"column"}],"isInner":"1","elType":"section"},{"id":"4f3eb9c3","settings":{"space":{"unit":"px","size":"403","sizes":[]},"_border_border":"solid","_border_width":{"unit":"px","top":"3","right":"3","bottom":"3","left":"3","isLinked":"1"},"_element_width":"initial","_element_width_tablet":"initial","_element_width_mobile":"initial","_element_custom_width":{"unit":"px","size":"840","sizes":[]},"_element_custom_width_tablet":{"unit":"vw","size":"78","sizes":[]},"_element_custom_width_mobile":{"unit":"vw","size":"67","sizes":[]},"_position":"absolute","_offset_x":{"unit":"px","size":"-50","sizes":[]},"_offset_x_mobile":{"unit":"px","size":"-40","sizes":[]},"_offset_y":{"unit":"px","size":"-40","sizes":[]},"_offset_y_mobile":{"unit":"px","size":"-40","sizes":[]},"__globals__":{"_border_color":"globals\/colors?id=a856848"},"_animation":"slideInUp"},"elements":[],"isInner":false,"widgetType":"spacer","elType":"widget"}],"isInner":"","elType":"column"}],"isInner":"","elType":"section"},{"id":"5a8b4f74","settings":{"gap":"no","height":"min-height","custom_height":{"unit":"px","size":"680","sizes":[]},"_title":"As Featured In","custom_height_tablet":{"unit":"vh","size":"34","sizes":[]},"custom_height_mobile":{"unit":"vh","size":"35","sizes":[]},"background_background":"classic","padding":{"unit":"%","top":"0","right":"4","bottom":"0","left":"4","isLinked":""},"padding_mobile":{"unit":"%","top":"10","right":"6","bottom":"10","left":"6","isLinked":""},"__globals__":{"background_color":""}},"elements":[{"id":"5ecd2061","settings":{"_column_size":"100"},"elements":[{"id":"461a6caf","settings":{"title":"As Featured In","_margin":{"unit":"%","top":"0","right":"0","bottom":"6","left":"0","isLinked":""},"_margin_tablet":{"unit":"%","top":"0","right":"0","bottom":"9","left":"0","isLinked":""},"align":"center","_margin_mobile":{"unit":"%","top":"0","right":"0","bottom":"12","left":"0","isLinked":""},"align_mobile":"center","_animation":"fadeIn"},"elements":[],"isInner":false,"widgetType":"heading","elType":"widget"},{"id":"311f44cc","settings":{"carousel":[{"id":"150","url":"https:\/\/library.elementor.com\/wedding-photographer\/wp-content\/uploads\/sites\/154\/2021\/05\/as-deatured-in-logo4.svg"},{"id":"148","url":"https:\/\/library.elementor.com\/wedding-photographer\/wp-content\/uploads\/sites\/154\/2021\/05\/as-deatured-in-logo2.svg"},{"id":"152","url":"https:\/\/library.elementor.com\/wedding-photographer\/wp-content\/uploads\/sites\/154\/2021\/05\/as-deatured-in-logo6.svg"},{"id":"147","url":"https:\/\/library.elementor.com\/wedding-photographer\/wp-content\/uploads\/sites\/154\/2021\/05\/as-deatured-in-logo1.svg"},{"id":"149","url":"https:\/\/library.elementor.com\/wedding-photographer\/wp-content\/uploads\/sites\/154\/2021\/05\/as-deatured-in-logo3.svg"}],"thumbnail_size":"full","slides_to_show":"5","slides_to_show_tablet":"3","slides_to_show_mobile":"2","slides_to_scroll":"1","slides_to_scroll_tablet":"2","slides_to_scroll_mobile":"2","navigation":"none","pause_on_hover":"no","pause_on_interaction":"no","autoplay_speed":"3000","gallery_vertical_align":"center","image_spacing_custom":{"unit":"px","size":"60","sizes":[]},"image_border_border":"solid","image_border_width":{"unit":"px","top":"0","right":"20","bottom":"0","left":"20","isLinked":""},"__globals__":{"image_border_color":"globals\/colors?id=4440aa9"}},"elements":[],"isInner":false,"widgetType":"image-carousel","elType":"widget"}],"isInner":"","elType":"column"}],"isInner":"","elType":"section"},{"id":"3c71ff61","settings":{"gap":"no","height":"min-height","custom_height":{"unit":"px","size":"557","sizes":[]},"background_background":"classic","__globals__":{"background_color":"globals\/colors?id=65e875c0"},"_title":"Call To Action","custom_height_mobile":{"unit":"vh","size":"80","sizes":[]},"padding":{"unit":"%","top":"","right":"","bottom":"","left":"","isLinked":"1"},"padding_mobile":{"unit":"%","top":"","right":"","bottom":"","left":"","isLinked":"1"},"layout":"full_width","column_position":"stretch","content_position":"middle","structure":"20"},"elements":[{"id":"4a3f4fd6","settings":{"_column_size":"50","_inline_size":"42.02","_inline_size_tablet":"45","padding":{"unit":"%","top":"0","right":"12","bottom":"0","left":"12","isLinked":""},"padding_mobile":{"unit":"%","top":"27","right":"8","bottom":"27","left":"8","isLinked":""}},"elements":[{"id":"7fdf8557","settings":{"title":"Get in Touch","_margin":{"unit":"%","top":"0","right":"0","bottom":"5","left":"0","isLinked":""},"_margin_tablet":{"unit":"%","top":"0","right":"0","bottom":"7","left":"0","isLinked":""},"align":"center","_margin_mobile":{"unit":"%","top":"0","right":"0","bottom":"12","left":"0","isLinked":""},"align_mobile":"center"},"elements":[],"isInner":false,"widgetType":"heading","elType":"widget"},{"id":"17889cd3","settings":{"editor":"Lorem ipsum dolor sit amet, consectetur adipiscing elit, sed do eiusmod tempor incididunt ut labore et dolore magna aliqua. Non consectetur a erat nam at ","align":"center"},"elements":[],"isInner":false,"widgetType":"text-editor","elType":"widget"},{"id":"2ec4fbc8","settings":{"text":"Contact Roberta \u27f6","align":"center","icon_align":"right","text_padding":{"unit":"px","top":"0","right":"0","bottom":"0","left":"0","isLinked":""},"_margin":{"unit":"%","top":"7","right":"0","bottom":"0","left":"0","isLinked":""},"__globals__":{"background_color":"globals\/colors?id=4440aa9","button_text_color":"globals\/colors?id=accent","hover_color":"globals\/colors?id=2ee8cc4b","button_background_hover_color":"globals\/colors?id=4440aa9"},"_margin_tablet":{"unit":"%","top":"12","right":"0","bottom":"0","left":"0","isLinked":""},"_margin_mobile":{"unit":"%","top":"14","right":"0","bottom":"0","left":"0","isLinked":""},"hover_animation":"hang","link":{"url":"https:\/\/library.elementor.com\/wedding-photographer\/contact\/","is_external":"","nofollow":"","custom_attributes":""}},"elements":[],"isInner":false,"widgetType":"button","elType":"widget"}],"isInner":"","elType":"column"},{"id":"3f38fded","settings":{"_column_size":"50","_inline_size":"57.966","_inline_size_tablet":"55","background_background":"classic","background_image":{"url":"https:\/\/library.elementor.com\/wedding-photographer\/wp-content\/uploads\/sites\/154\/2021\/05\/footer-pic-tall.jpg","id":"166"},"background_position":"center right","background_position_tablet":"initial","background_xpos_tablet":{"unit":"%","size":"53","sizes":[]},"background_ypos_tablet":{"unit":"%","size":"68","sizes":[]},"background_attachment":"fixed","background_repeat":"no-repeat"},"elements":[{"id":"66863cb4","settings":{"space_mobile":{"unit":"vh","size":"70","sizes":[]}},"elements":[],"isInner":false,"widgetType":"spacer","elType":"widget"}],"isInner":"","elType":"column"}],"isInner":"","elType":"section"}],"settings":{"template":"default","hide_title":"yes"},"metadata":[]}